AUTHORS
LICENSE
MANIFEST.in
README.rst
setup.py
django_wysihtml5.egg-info/PKG-INFO
django_wysihtml5.egg-info/SOURCES.txt
django_wysihtml5.egg-info/dependency_links.txt
django_wysihtml5.egg-info/top_level.txt
wysihtml5/__init__.py
wysihtml5/admin.py
wysihtml5/fields.py
wysihtml5/models.py
wysihtml5/utils.py
wysihtml5/widgets.py
wysihtml5/conf/__init__.py
wysihtml5/conf/defaults.py
wysihtml5/static/wysihtml5/css/stylesheet.css
wysihtml5/static/wysihtml5/css/toolbar.css
wysihtml5/static/wysihtml5/img/toolbar.png
wysihtml5/static/wysihtml5/js/advanced.js
wysihtml5/static/wysihtml5/js/simple.js
wysihtml5/static/wysihtml5/js/wysihtml5-0.3.0.min.js
wysihtml5/static/wysihtml5/js/wysihtml5-0.4.0pre.min.js
wysihtml5/tests/__init__.py
wysihtml5/tests/fields.py
wysihtml5/tests/models.py
wysihtml5/tests/settings.py
wysihtml5/tests/widgets.py