Metadata-Version: 1.1
Name: django-wysihtml5
Version: 1.2b2
Summary: Simple Django app that provides a Wysihtml5 rich text editor textarea widget.
Home-page: http://pypi.python.org/pypi/django-wysihtml5/
Author: Daniel Rus Morales
Author-email: inbox@danir.us
License: MIT
Platform: UNKNOWN
Classifier: Development Status :: 4 - Beta
Classifier: Environment :: Web Environment
Classifier: Intended Audience :: Developers
Classifier: License :: OSI Approved :: MIT License
Classifier: Operating System :: OS Independent
Classifier: Programming Language :: Python
Classifier: Programming Language :: Python :: 3
Classifier: Framework :: Django
